setup.py
gogger/__init__.py
gogger/level_filter.py
gogger.egg-info/PKG-INFO
gogger.egg-info/SOURCES.txt
gogger.egg-info/dependency_links.txt
gogger.egg-info/top_level.txt