Metadata-Version: 1.0
Name: gogger
Version: 0.0.5
Summary: Logger creator
Home-page: UNKNOWN
Author: peixiaohan
Author-email: xiaohan@bigonelab.com
License: UNKNOWN
Platform: UNKNOWN
